kye/__about__.py
kye/__init__.py
kye/cli.py
kye/compiled.py
kye/kye.py
kye/native_types.kye.json
kye/source_map.py
kye/errors/base_reporter.py
kye/errors/compilation_errors.py
kye/errors/exceptions.py
kye/errors/validation_errors.py
kye/parse/desugar.py
kye/parse/expressions.py
kye/parse/grammar.lark
kye/parse/parser.py
kye/type/compiler.py
kye/type/native_types.py
kye/type/type_builder.py
kye/type/types.py
kye/vm/loader.py
kye/vm/op.py
kye/vm/vm.py
kye-0.1.2.dist-info/METADATA
kye-0.1.2.dist-info/WHEEL
kye-0.1.2.dist-info/entry_points.txt
kye-0.1.2.dist-info/licenses/LICENSE
kye-0.1.2.dist-info/RECORD
