Metadata-Version: 2.3
Name: kye
Version: 0.1.2
Summary: A Data Validation Framework
Project-URL: Documentation, https://github.com/kyelabs/kyepy#readme
Project-URL: Issues, https://github.com/kyelabs/kyepy/issues
Project-URL: Source, https://github.com/kyelabs/kyepy
Author-email: Benjamin Earl <14208829+benjameep@users.noreply.github.com>
License-Expression: MIT
License-File: LICENSE
Classifier: License :: OSI Approved :: MIT License
Classifier: Programming Language :: Python :: 3
Requires-Python: >=3.7
Requires-Dist: lark
Requires-Dist: lark[interegular]
